{
   "accentFromPage": false,
   "accentOnWindow": true,
   "accentSaturationLimit": 1,
   "alpha": 1,
   "backgroundImage": "",
   "backgroundPosition": "stretch",
   "blur": 5,
   "colorAccentBg": "#49483e",
   "colorBg": "#272822",
   "colorFg": "#f8f8f2",
   "colorHighlightBg": "#a6e22e",
   "colorWindowBg": "",
   "contrast": 0,
   "dimBlurred": false,
   "engineVersion": 1,
   "id": "54a8d0da-0902-41a2-b0c4-d42866140772",
   "name": "Monokai",
   "preferSystemAccent": false,
   "radius": 14,
   "simpleScrollbar": false,
   "transparencyTabBar": false,
   "transparencyTabs": true,
   "url": "",
   "version": 1
}